MANIFEST.in
README.md
README.rst
requirements.txt
setup.py
jdodata/__init__.py
jdodata.egg-info/PKG-INFO
jdodata.egg-info/SOURCES.txt
jdodata.egg-info/dependency_links.txt
jdodata.egg-info/requires.txt
jdodata.egg-info/top_level.txt
jdodata.egg-info/zip-safe
jdodata/utils/CONST.py
jdodata/utils/http.py
jdodata/utils/user.py