Metadata-Version: 2.1
Name: jdodata
Version: 1.0.13
Summary: Jianda Open Data
Home-page: UNKNOWN
Author: @wukehao
Author-email: wukehao@jddatatech.com
License: MIT
Keywords: 简答数据,jianda,jianda data,open data
Platform: UNKNOWN
Classifier: Development Status :: 5 - Production/Stable
Classifier: License :: OSI Approved :: Apache Software License
Classifier: Programming Language :: Python :: 3
Classifier: Programming Language :: Python :: 3.5
Classifier: Programming Language :: Python :: 3.6
Classifier: Programming Language :: Python :: 3.7
Classifier: Programming Language :: Python :: 3.8
Classifier: Programming Language :: Python :: 3.9
Classifier: Programming Language :: Python :: 3.10
Classifier: Topic :: Office/Business :: Financial
